src/__init__.py
src/main.py
src/core/__init__.py
src/core/lab_manager.py
src/core/terminal.py
src/data/__init__.py
src/data/lessons.py
src/ui/__init__.py
src/ui/formatting.py
src/ui/menu.py
src/utils/__init__.py
src/utils/helpers.py
linux_buddy-1.0.2.dist-info/METADATA
linux_buddy-1.0.2.dist-info/WHEEL
linux_buddy-1.0.2.dist-info/entry_points.txt
linux_buddy-1.0.2.dist-info/top_level.txt
linux_buddy-1.0.2.dist-info/RECORD
