Metadata-Version: 2.4
Name: linux-buddy
Version: 1.0.2
Summary: Interactive Linux command tutorial with hands-on terminal labs for beginners and ethical hackers
Author-email: jo4dan <jordannissi7@gmail.com>
Maintainer-email: jo4dan <jordannissi7@gmail.com>
License: GPL-3.0-or-later
Project-URL: Homepage, https://github.com/jo4dan/linux-buddy
Project-URL: Repository, https://github.com/jo4dan/linux-buddy
Project-URL: Issues, https://github.com/jo4dan/linux-buddy/issues
Project-URL: Changelog, https://github.com/jo4dan/linux-buddy/releases
Keywords: linux,tutorial,command-line,cli,education,ethical-hacking,cybersecurity,devops,terminal,learning-tool,beginner,practice-labs
Classifier: Development Status :: 4 - Beta
Classifier: Intended Audience :: Education
Classifier: Intended Audience :: Developers
Classifier: Intended Audience :: System Administrators
Classifier: Topic :: Education
Classifier: Topic :: System :: Systems Administration
Classifier: Topic :: Security
Classifier: License :: OSI Approved :: GNU General Public License v3 or later (GPLv3+)
Classifier: Programming Language :: Python :: 3
Classifier: Programming Language :: Python :: 3.6
Classifier: Programming Language :: Python :: 3.7
Classifier: Programming Language :: Python :: 3.8
Classifier: Programming Language :: Python :: 3.9
Classifier: Programming Language :: Python :: 3.10
Classifier: Programming Language :: Python :: 3.11
Classifier: Programming Language :: Python :: 3.12
Classifier: Programming Language :: Python :: 3.13
Classifier: Operating System :: POSIX :: Linux
Classifier: Operating System :: Unix
Classifier: Environment :: Console
Requires-Python: >=3.6
